radioutils/__init__.py
radioutils/distrssi.py
radioutils/impairments.py
radioutils/plots.py
radioutils-1.4.0.dist-info/DESCRIPTION.rst
radioutils-1.4.0.dist-info/METADATA
radioutils-1.4.0.dist-info/RECORD
radioutils-1.4.0.dist-info/WHEEL
radioutils-1.4.0.dist-info/metadata.json
radioutils-1.4.0.dist-info/top_level.txt
