Metadata-Version: 2.0
Name: radioutils
Version: 1.4.0
Summary: Low-level radio communications modeling utilitiesincluding AM, FM, SSB/DSB demodulation of GNU Radio data
Home-page: https://github.com/scivision/radioutils
Author: Michael Hirsch, Ph.D.
Author-email: UNKNOWN
License: UNKNOWN
Platform: UNKNOWN
Classifier: Intended Audience :: Science/Research
Classifier: Development Status :: 4 - Beta
Classifier: License :: OSI Approved :: MIT License
Classifier: Topic :: Scientific/Engineering :: Mathematics
Classifier: Programming Language :: Python :: 3
Requires-Dist: matplotlib
Requires-Dist: nose
Requires-Dist: numpy
Requires-Dist: scipy
Requires-Dist: seaborn
